chainer_cv/__init__.py
chainer_cv/datasets/__init__.py
chainer_cv/datasets/image_retrieval/__init__.py
chainer_cv/datasets/image_retrieval/online_products_dataset.py
chainer_cv/datasets/semantic_segmentation/__init__.py
chainer_cv/datasets/semantic_segmentation/pascal_voc_dataset.py
chainer_cv/evaluations/__init__.py
chainer_cv/evaluations/eval_semantic_segmentation.py
chainer_cv/extensions/__init__.py
chainer_cv/extensions/embed_images.py
chainer_cv/extensions/utils.py
chainer_cv/extensions/image_retrieval/__init__.py
chainer_cv/extensions/image_retrieval/measure_k_recall.py
chainer_cv/extensions/semantic_segmentation/__init__.py
chainer_cv/extensions/semantic_segmentation/semantic_segmentation_vis_out.py
chainer_cv/external/__init__.py
chainer_cv/external/tensorboard/__init__.py
chainer_cv/external/tensorboard/embedding_tensorboard.py
chainer_cv/functions/__init__.py
chainer_cv/models/__init__.py
chainer_cv/models/googlenet.py
chainer_cv/testing/__init__.py
chainer_cv/testing/helper.py
chainer_cv/training/__init__.py
chainer_cv/training/test_mode_evaluator.py
chainer_cv/utils/__init__.py
chainer_cv/utils/download.py
chainer_cv/wrappers/__init__.py
chainer_cv/wrappers/cache_array_dataset_wrapper.py
chainer_cv/wrappers/cache_dataset_wrapper.py
chainer_cv/wrappers/dataset_wrapper.py
chainer_cv/wrappers/pad_wrapper.py
chainer_cv/wrappers/subtract_wrapper.py
chainer_cv/wrappers/cache_dataset/__init__.py
chainer_cv/wrappers/cache_dataset/cache_array_dataset_wrapper.py
chainer_cv/wrappers/cache_dataset/cache_dataset_wrapper.py
chainer_cv/wrappers/data_augmentation/__init__.py
chainer_cv/wrappers/data_augmentation/crop_wrapper.py
chainer_cv/wrappers/data_augmentation/random_mirror_wrapper.py
chainer_cv/wrappers/preprocessing/__init__.py
chainer_cv/wrappers/preprocessing/pad_wrapper.py
chainer_cv/wrappers/preprocessing/resize_wrapper.py
chainer_cv/wrappers/preprocessing/subtract_wrapper.py
chainercv-0.4.5.dist-info/DESCRIPTION.rst
chainercv-0.4.5.dist-info/METADATA
chainercv-0.4.5.dist-info/RECORD
chainercv-0.4.5.dist-info/WHEEL
chainercv-0.4.5.dist-info/metadata.json
chainercv-0.4.5.dist-info/top_level.txt
