Metadata-Version: 2.0
Name: chainercv
Version: 0.4.5
Summary: 
Requires-Dist: chainer (>=1.21)
Requires-Dist: pillow
